AndroidUiAutomation.py
android_ui_automation/__init__.py
android_ui_automation/android_ui_library.py
robotframework_androiduiautomation-0.2.0.dist-info/licenses/LICENSE
robotframework_androiduiautomation-0.2.0.dist-info/METADATA
robotframework_androiduiautomation-0.2.0.dist-info/WHEEL
robotframework_androiduiautomation-0.2.0.dist-info/top_level.txt
robotframework_androiduiautomation-0.2.0.dist-info/RECORD
