Metadata-Version: 2.4
Name: robotframework-androiduiautomation
Version: 0.2.0
Summary: Robot Framework library for Android automation using uiautomator2
Author: Valter I F de Souza
Requires-Python: >=3.8
License-File: LICENSE
Requires-Dist: uiautomator2
Requires-Dist: robotframework
Dynamic: author
Dynamic: description
Dynamic: description-content-type
Dynamic: license-file
Dynamic: requires-dist
Dynamic: requires-python
Dynamic: summary
